{
  "ABCDEFGL": ["3C", "3G", "3B", "3D", "3A", "3F", "3L", "3E"],
  "ABCDEHKL": ["3H", "3E", "3B", "3C", "3A", "3D", "3L", "3K"],
  "ABCDFGHK": ["3H", "3G", "3B", "3C", "3A", "3F", "3D", "3K"],
  "ABCDFGHL": ["3C", "3G", "3B", "3D", "3A", "3F", "3L", "3H"],
  "ABCDFGIL": ["3C", "3G", "3B", "3D", "3A", "3F", "3L", "3I"],
  "ABCDFGJL": ["3C", "3G", "3B", "3D", "3A", "3F", "3L", "3J"],
  "ABCDFHKL": ["3H", "3F", "3B", "3C", "3A", "3D", "3L", "3K"],
  "ABCDGJKL": ["3C", "3J", "3B", "3D", "3A", "3G", "3L", "3K"],
  "ABCDHIKL": ["3H", "3I", "3B", "3C", "3A", "3D", "3L", "3K"],
  "ABCDHJKL": ["3H", "3J", "3B", "3C", "3A", "3D", "3L", "3K"],
  "ABCEFGHK": ["3H", "3G", "3B", "3C", "3A", "3F", "3E", "3K"],
  "ABCEIJKL": ["3E", "3J", "3B", "3A", "3I", "3C", "3L", "3K"],
  "ABCFGHIK": ["3H", "3G", "3B", "3C", "3A", "3F", "3I", "3K"],
  "ABCFGHJK": ["3H", "3G", "3B", "3C", "3A", "3F", "3J", "3K"],
  "ABCFGHKL": ["3H", "3G", "3B", "3C", "3A", "3F", "3L", "3K"],
  "ABDEGJKL": ["3E", "3J", "3B", "3D", "3A", "3G", "3L", "3K"],
  "ABDEIJKL": ["3E", "3J", "3B", "3A", "3I", "3D", "3L", "3K"],
  "ABDFGJKL": ["3F", "3J", "3B", "3D", "3A", "3G", "3L", "3K"],
  "ABDGHJKL": ["3H", "3J", "3B", "3D", "3A", "3G", "3L", "3K"],
  "ABDGIJKL": ["3I", "3J", "3B", "3D", "3A", "3G", "3L", "3K"],
  "ABEFIJKL": ["3E", "3J", "3B", "3A", "3I", "3F", "3L", "3K"],
  "ABEGIJKL": ["3E", "3J", "3B", "3A", "3I", "3G", "3L", "3K"],
  "ABEHIJKL": ["3E", "3J", "3B", "3A", "3I", "3H", "3L", "3K"],
  "ACDEGHKL": ["3H", "3G", "3E", "3C", "3A", "3D", "3L", "3K"],
  "ACDFGHKL": ["3H", "3G", "3F", "3C", "3A", "3D", "3L", "3K"],
  "ACDGHIKL": ["3H", "3G", "3I", "3C", "3A", "3D", "3L", "3K"],
  "ACDGHJKL": ["3H", "3G", "3J", "3C", "3A", "3D", "3L", "3K"],
  "AEGHIJKL": ["3E", "3J", "3I", "3A", "3H", "3G", "3L", "3K"],
  "BCDEFGKL": ["3C", "3G", "3B", "3D", "3E", "3F", "3L", "3K"],
  "BCDFGHKL": ["3C", "3G", "3B", "3D", "3H", "3F", "3L", "3K"],
  "BCDFGIKL": ["3C", "3G", "3B", "3D", "3I", "3F", "3L", "3K"],
  "BCDFGJKL": ["3C", "3G", "3B", "3D", "3J", "3F", "3L", "3K"],
  "BEGHIJKL": ["3E", "3J", "3I", "3B", "3H", "3G", "3L", "3K"],
  "CEGHIJKL": ["3E", "3J", "3I", "3C", "3H", "3G", "3L", "3K"],
  "DEGHIJKL": ["3E", "3J", "3I", "3D", "3H", "3G", "3L", "3K"],
  "EFGHIJKL": ["3E", "3J", "3I", "3F", "3H", "3G", "3L", "3K"]
}
